ctwin32/__init__.py
ctwin32/advapi.py
ctwin32/bcrypt.py
ctwin32/cfgmgr.py
ctwin32/comctl.py
ctwin32/dbghelp.py
ctwin32/gdi.py
ctwin32/iphlpapi.py
ctwin32/kernel.py
ctwin32/kuser_shared_data.py
ctwin32/msi.py
ctwin32/ntdll.py
ctwin32/pemap.py
ctwin32/powrprof.py
ctwin32/psapi.py
ctwin32/secur.py
ctwin32/setupapi.py
ctwin32/shell.py
ctwin32/svc_util.py
ctwin32/user.py
ctwin32/userenv.py
ctwin32/version.py
ctwin32/virtdisk.py
ctwin32/wndcls.py
ctwin32/wtsapi.py
ctwin32/wtypes.py
ctwin32-4.0.0.dist-info/licenses/LICENSE
ctwin32-4.0.0.dist-info/METADATA
ctwin32-4.0.0.dist-info/WHEEL
ctwin32-4.0.0.dist-info/top_level.txt
ctwin32-4.0.0.dist-info/RECORD
