Metadata-Version: 2.4
Name: ctwin32
Version: 4.0.0
Summary: Access selected win32 APIs through ctypes
Author: Rocco Matano
License-Expression: MIT
Project-URL: homepage, https://github.com/RoccoMatano/ctwin32
Project-URL: changelog, https://github.com/RoccoMatano/ctwin32/blob/master/changelog.md
Classifier: Programming Language :: Python
Classifier: Operating System :: Microsoft :: Windows
Classifier: Environment :: Win32 (MS Windows)
Classifier: Intended Audience :: Developers
Classifier: Programming Language :: Python :: 3.10
Classifier: Programming Language :: Python :: 3.11
Classifier: Programming Language :: Python :: 3.12
Classifier: Programming Language :: Python :: 3.13
Classifier: Programming Language :: Python :: 3.14
Requires-Python: >=3.10
License-File: LICENSE
Dynamic: license-file
